{"Modules":[{"Key":"","Source":"","Dir":"."},{"Key":"compute","Source":"./modules/compute","Dir":"modules/compute"},{"Key":"database","Source":"./modules/database","Dir":"modules/database"},{"Key":"iam","Source":"./modules/iam","Dir":"modules/iam"},{"Key":"load_balancer","Source":"./modules/load-balancer","Dir":"modules/load-balancer"},{"Key":"security","Source":"./modules/security","Dir":"modules/security"},{"Key":"storage","Source":"./modules/storage","Dir":"modules/storage"},{"Key":"vpc","Source":"./modules/vpc","Dir":"modules/vpc"}]}